code_review/__init__.py
code_review/cli.py
code_review/config.py
code_review/enums.py
code_review/exceptions.py
code_review/schemas.py
code_review/settings.py
code_review/adapters/__init__.py
code_review/adapters/changelog.py
code_review/adapters/generics.py
code_review/adapters/setup_adapters.py
code_review/handlers/__init__.py
code_review/handlers/display_handlers.py
code_review/handlers/file_handlers.py
code_review/plugins/__init__.py
code_review/plugins/coverage/__init__.py
code_review/plugins/coverage/handlers.py
code_review/plugins/coverage/main.py
code_review/plugins/coverage/schemas.py
code_review/plugins/dependencies/__init__.py
code_review/plugins/dependencies/pip/__init__.py
code_review/plugins/dependencies/pip/handlers.py
code_review/plugins/dependencies/pip/schemas.py
code_review/plugins/dependencies/poetry/__init__.py
code_review/plugins/docker/__init__.py
code_review/plugins/docker/schemas.py
code_review/plugins/docker/docker_files/__init__.py
code_review/plugins/docker/docker_files/adapters.py
code_review/plugins/docker/docker_files/handlers.py
code_review/plugins/docker/docker_hub/__init__.py
code_review/plugins/docker/docker_hub/main.py
code_review/plugins/docker/docker_hub/schemas.py
code_review/plugins/docker/docker_hub/filters/__init__.py
code_review/plugins/docker/docker_hub/filters/exclusions.py
code_review/plugins/docker/docker_hub/filters/inclusions.py
code_review/plugins/git/__init__.py
code_review/plugins/git/adapters.py
code_review/plugins/git/handlers.py
code_review/plugins/git/main.py
code_review/plugins/gitlab/__init__.py
code_review/plugins/gitlab/ci/__init__.py
code_review/plugins/gitlab/ci/handlers.py
code_review/plugins/gitlab/ci/rules.py
code_review/plugins/linting/__init__.py
code_review/plugins/linting/ast/__init__.py
code_review/plugins/linting/ruff/__init__.py
code_review/plugins/linting/ruff/handlers.py
code_review/plugins/linting/ruff/main.py
code_review/review/__init__.py
code_review/review/adapters.py
code_review_plus-0.12.0.dist-info/METADATA
code_review_plus-0.12.0.dist-info/WHEEL
code_review_plus-0.12.0.dist-info/entry_points.txt
code_review_plus-0.12.0.dist-info/top_level.txt
code_review_plus-0.12.0.dist-info/RECORD
