Metadata-Version: 2.4
Name: code-review-plus
Version: 0.12.0
Summary: Add your description here
Requires-Python: >=3.10
Requires-Dist: ast2json>=0.4
Requires-Dist: click>=8.2.1
Requires-Dist: deprecated>=1.2.18
Requires-Dist: gitignore-parser>=0.1.13
Requires-Dist: pur>=7.3.3
Requires-Dist: pyaml>=25.7.0
Requires-Dist: pydantic>=2.11.7
Requires-Dist: python-dotenv>=1.1.1
Requires-Dist: requests>=2.32.5
Requires-Dist: rich>=14.1.0
Requires-Dist: toml>=0.10.2
